[
    {
        "kategoria": "Wydarzenie",
        "slowaHasla": [
            "BALLADYNA",
            "ZABIJA",
            "ALINĘ"
        ]
    },
    {
        "kategoria": "Pojęcie",
        "slowaHasla": [
            "MALINOWY",
            "KONKURS"
        ]
    },
    {
        "kategoria": "Wydarzenie",
        "slowaHasla": [
            "ŚMIERĆ",
            "BALLADYNY"
        ]
    },
    {
        "kategoria": "Wydarzenie",
        "slowaHasla": [
            "BALLADYNA",
            "ZASIADA",
            "NA",
            "TRONIE"
        ]
    },
    {
        "kategoria": "Pojęcie",
        "slowaHasla": [
            "KRWAWA",
            "PLAMA",
            "NA",
            "CZOLE",
            "BALLADYNY"
        ]
    },
    {
        "kategoria": "Bohater",
        "slowaHasla": [
            "SKIERKA",
            "I",
            "CHOCHLIK"
        ]
    },
    {
        "kategoria": "Wydarzenie",
        "slowaHasla": [
            "PUSTELNIK",
            "RADZI",
            "KIRKOROWI"
        ]
    },
    {
        "kategoria": "Miejsce",
        "slowaHasla": [
            "JEZIORO",
            "GOPŁO"
        ]
    }
]